trame/__init__.py
trame/modules/__init__.py
trame/modules/grid.py
trame/widgets/__init__.py
trame/widgets/grid.py
trame_grid/__init__.py
trame_grid/module/__init__.py
trame_grid/module/serve/vue-grid-layout.js
trame_grid/widgets/__init__.py
trame_grid/widgets/grid.py
trame_grid_layout-1.0.3.dist-info/LICENSE
trame_grid_layout-1.0.3.dist-info/METADATA
trame_grid_layout-1.0.3.dist-info/WHEEL
trame_grid_layout-1.0.3.dist-info/top_level.txt
trame_grid_layout-1.0.3.dist-info/RECORD
