Metadata-Version: 2.1
Name: trame-grid-layout
Version: 1.0.3
Summary: Trame wrapper to vue-grid-layout
Author: Kitware Inc.
License: MIT License
Keywords: Python,Interactive,Web,Application,Framework
Classifier: Development Status :: 5 - Production/Stable
Classifier: Environment :: Web Environment
Classifier: License :: OSI Approved :: MIT License
Classifier: Natural Language :: English
Classifier: Operating System :: OS Independent
Classifier: Programming Language :: Python :: 3 :: Only
Classifier: Programming Language :: JavaScript
Classifier: Topic :: Software Development :: Libraries :: Application Frameworks
Classifier: Topic :: Software Development :: Libraries :: Python Modules
License-File: LICENSE
Requires-Dist: trame-client
